encoded_client/__init__.py
encoded_client/_version.py
encoded_client/encoded.py
encoded_client/hashfile.py
encoded_client/metadata.py
encoded_client/rdfhelp.py
encoded_client/rdfns.py
encoded_client/sheet.py
encoded_client/submission.py
encoded_client/schemas/dc.turtle
encoded_client/schemas/htsworkflow.turtle
encoded_client/schemas/owl.turtle
encoded_client/schemas/rdf.turtle
encoded_client/schemas/rdfs.turtle
encoded_client/schemas/xhtmlvocab.turtle
encoded_client/tests/__init__.py
encoded_client/tests/biosample.json
encoded_client/tests/extra.turtle
encoded_client/tests/file.json
encoded_client/tests/library.json
encoded_client/tests/star_solo_quality_metric.json
encoded_client/tests/test_encoded.py
encoded_client/tests/test_hashfile.py
encoded_client/tests/test_metadata.py
encoded_client/tests/test_rdfhelp.py
encoded_client/tests/test_sheet.py
encoded_client/tests/test_submission.py
encoded_client-0.3.0.dist-info/LICENSE.txt
encoded_client-0.3.0.dist-info/METADATA
encoded_client-0.3.0.dist-info/WHEEL
encoded_client-0.3.0.dist-info/entry_points.txt
encoded_client-0.3.0.dist-info/top_level.txt
encoded_client-0.3.0.dist-info/RECORD
