Metadata-Version: 2.1
Name: encoded-client
Version: 0.3.0
Summary: interface to the ENCODE DCC portal
Author: Diane Trout
Author-email: diane@caltech.edu
License: BSD-3
Project-URL: Source, https://github.com/detrout/encoded_client
Project-URL: Tracker, https://github.com/detrout/encoded_client
License-File: LICENSE.txt
Requires-Dist: jsonschema
Requires-Dist: pandas
Requires-Dist: requests
Requires-Dist: awscli
Provides-Extra: doc
Requires-Dist: sphinx ; extra == 'doc'
Provides-Extra: rdf
Requires-Dist: lxml (>=2.2.4) ; extra == 'rdf'
Requires-Dist: rdflib ; extra == 'rdf'
Provides-Extra: submit
Requires-Dist: awscli ; extra == 'submit'
Provides-Extra: test
Requires-Dist: pytest ; extra == 'test'
Requires-Dist: pytest-cov ; extra == 'test'
Requires-Dist: openpyxl ; extra == 'test'
Requires-Dist: setuptools-scm ; extra == 'test'
Requires-Dist: xlsxwriter ; extra == 'test'
Requires-Dist: xlwt ; extra == 'test'
